tabela_sac/__init__.py
tabela_sac/_modidx.py
tabela_sac/cli.py
tabela_sac/core.py
tabela_sac-2.0.0.dist-info/LICENSE
tabela_sac-2.0.0.dist-info/METADATA
tabela_sac-2.0.0.dist-info/WHEEL
tabela_sac-2.0.0.dist-info/entry_points.txt
tabela_sac-2.0.0.dist-info/top_level.txt
tabela_sac-2.0.0.dist-info/RECORD
