Metadata-Version: 2.1
Name: tabela-sac
Version: 2.0.0
Summary: Forma Simples de Gerar uma Tabela SAC
Home-page: https://github.com/joaopcnogueira/tabela-sac
Author: João Paulo Nogueira
Author-email: joaopcnogueira@gmail.com
License: Apache Software License 2.0
Keywords: nbdev jupyter notebook python
Classifier: Development Status :: 4 - Beta
Classifier: Intended Audience :: Developers
Classifier: Natural Language :: English
Classifier: Programming Language :: Python :: 3.7
Classifier: Programming Language :: Python :: 3.8
Classifier: Programming Language :: Python :: 3.9
Classifier: Programming Language :: Python :: 3.10
Classifier: License :: OSI Approved :: Apache Software License
Requires-Python: >=3.7
License-File: LICENSE
Requires-Dist: fastcore
Requires-Dist: pandas
Provides-Extra: dev
Requires-Dist: jupyter ; extra == 'dev'
